mongo_m/__init__.py
mongo_m/__main__.py
mongo_m/core/__init__.py
mongo_m/core/creator.py
mongo_m/core/ini_file.py
mongo_m/core/inspect_module.py
mongo_m/core/mongodb.py
mongo_m/core/utils.py
mongo_m/repository/__init__.py
mongo_m/repository/collections/__init__.py
mongo_m/repository/collections/collections.py
mongo_m/repository/collections/models.py
mongo_m/repository/collections/query.py
mongo_m/services/__init__.py
mongo_m/services/migration/__init__.py
mongo_m/services/migration/file.py
mongo_m/services/migration/migration.py
tests/__init__.py
mongo_m-1.1.5.1.dist-info/METADATA
mongo_m-1.1.5.1.dist-info/WHEEL
mongo_m-1.1.5.1.dist-info/top_level.txt
mongo_m-1.1.5.1.dist-info/RECORD
